[
  {
    "reward": 941.3775226252095,
    "parameters": {
      "steps": 2,
      "multiplier": 0.95,
      "stopLoss": -23,
      "leverReduce": -8
    },
    "rest": {
      "trades": 21,
      "identifier": "optimized_2_0.95_-23_-8-SOL-USDT-SWAP-11rz",
      "name": "optimized_2_0.95_-23_-8",
      "startCapital": 200,
      "symbol": "SOL-USDT-SWAP",
      "margin": 1040.1000000000001,
      "pnl": 1886.25,
      "winRatio": 0.5714285714285714,
      "time": "2024-07-06T22:20:13.131Z",
      "start": "2024-01-01T00:00:00.000Z",
      "end": "2024-07-04T19:17:00.000Z",
      "pnl_pct": 943.1233151781338,
      "hodl_pct": 32.07510075690554,
      "liquidations": 8,
      "exchange": "okx",
      "hodl_ratio": 29.403596338667338,
      "maxDrawdown": 11.189059462190698,
      "sharpeRatio": 0.5831998231717916,
      "_id": "6689c31ddf1e57b18e0dce13"
    },
    "identifier": "optimized_2_0.95_-23_-8-SOL-USDT-SWAP-11rz"
  },
  {
    "reward": 275363.2202625565,
    "parameters": {
      "steps": 2,
      "multiplier": 0.86,
      "stopLoss": -12,
      "leverReduce": -23
    },
    "rest": {
      "trades": 101,
      "identifier": "optimized_2_0.86_-12_-23-PEPE-USDT-SWAP-mT9X",
      "name": "optimized_2_0.86_-12_-23",
      "startCapital": 200,
      "symbol": "PEPE-USDT-SWAP",
      "margin": 263279.43999999994,
      "pnl": 551154.84,
      "winRatio": 0.33663366336633666,
      "time": "2024-07-06T22:26:04.586Z",
      "start": "2024-01-01T00:00:00.000Z",
      "end": "2024-07-04T19:18:00.000Z",
      "pnl_pct": 275577.420804723,
      "hodl_pct": 640.3861003861003,
      "liquidations": 70,
      "exchange": "okx",
      "hodl_ratio": 430.33010966130024,
      "maxDrawdown": 2073.007275424999,
      "sharpeRatio": 5.748078209524374,
      "_id": "6689c47cdf1e57b18e0dd427"
    },
    "identifier": "optimized_2_0.86_-12_-23-PEPE-USDT-SWAP-mT9X"
  },
  {
    "reward": 14376.142811226537,
    "parameters": {
      "steps": 5,
      "multiplier": 1.03,
      "stopLoss": -26,
      "leverReduce": -18
    },
    "rest": {
      "trades": 9,
      "identifier": "optimized_5_1.03_-26_-18-NOT-USDT-SWAP-XAxA",
      "name": "optimized_5_1.03_-26_-18",
      "startCapital": 200,
      "symbol": "NOT-USDT-SWAP",
      "margin": 34237.384099999996,
      "pnl": 29003.47,
      "winRatio": 0.1111111111111111,
      "time": "2024-07-06T22:33:20.377Z",
      "start": "2024-01-01T00:00:00.000Z",
      "end": "2024-07-04T19:18:00.000Z",
      "pnl_pct": 14501.736797585641,
      "hodl_pct": 126.13701784686238,
      "liquidations": 7,
      "exchange": "okx",
      "hodl_ratio": 114.96812787497154,
      "maxDrawdown": 1249.2552210679628,
      "sharpeRatio": 0.26175132395210987,
      "_id": "6689c630df1e57b18e0dddab"
    },
    "identifier": "optimized_5_1.03_-26_-18-NOT-USDT-SWAP-XAxA"
  },
  {
    "reward": 410531.04293795384,
    "parameters": {
      "steps": 2,
      "multiplier": 0.87,
      "stopLoss": -21,
      "leverReduce": -11
    },
    "rest": {
      "trades": 82,
      "identifier": "optimized_2_0.87_-21_-11-PEOPLE-USDT-SWAP-N6Gn",
      "name": "optimized_2_0.87_-21_-11",
      "startCapital": 200,
      "symbol": "PEOPLE-USDT-SWAP",
      "margin": 413775.29000000004,
      "pnl": 821722.61,
      "winRatio": 0.47560975609756095,
      "time": "2024-07-06T22:45:37.192Z",
      "start": "2024-01-01T00:00:00.000Z",
      "end": "2024-07-04T19:18:00.000Z",
      "pnl_pct": 410861.3049840678,
      "hodl_pct": 368.7793427230047,
      "liquidations": 50,
      "exchange": "okx",
      "hodl_ratio": 1114.1114953737294,
      "maxDrawdown": 3254.0474497299965,
      "sharpeRatio": 6.91908298905533,
      "_id": "6689c911df1e57b18e0dee03"
    },
    "identifier": "optimized_2_0.87_-21_-11-PEOPLE-USDT-SWAP-N6Gn"
  },
  {
    "reward": 22.536342342252382,
    "parameters": {
      "steps": 10,
      "multiplier": 0.86,
      "stopLoss": -14,
      "leverReduce": -9
    },
    "rest": {
      "trades": 63,
      "identifier": "optimized_10_0.86_-14_-9-ORDI-USDT-SWAP-6gUO",
      "name": "optimized_10_0.86_-14_-9",
      "startCapital": 200,
      "symbol": "ORDI-USDT-SWAP",
      "margin": 4.04352663455,
      "pnl": 53.59,
      "winRatio": 0.2698412698412698,
      "time": "2024-07-06T22:59:17.882Z",
      "start": "2024-01-01T00:00:00.000Z",
      "end": "2024-07-06T09:14:00.000Z",
      "pnl_pct": 26.796367726726654,
      "hodl_pct": -64.26576903951346,
      "liquidations": 43,
      "exchange": "okx",
      "hodl_ratio": 0.4169617531574399,
      "maxDrawdown": 0.3961003869999995,
      "sharpeRatio": 62.407938927948585,
      "_id": "6689cc45df1e57b18e0e0395"
    },
    "identifier": "optimized_10_0.86_-14_-9-ORDI-USDT-SWAP-6gUO"
  },
  {
    "reward": 18.885,
    "parameters": {
      "steps": 5,
      "multiplier": 1.14,
      "stopLoss": -28,
      "leverReduce": -23
    },
    "rest": {
      "trades": 1,
      "identifier": "optimized_5_1.14_-28_-23-DOGE-USDT-SWAP-qqnF",
      "name": "optimized_5_1.14_-28_-23",
      "startCapital": 200,
      "symbol": "DOGE-USDT-SWAP",
      "margin": 37.665,
      "pnl": 37.17,
      "winRatio": 1,
      "time": "2024-07-06T23:01:46.310Z",
      "start": "2024-01-01T00:00:00.000Z",
      "end": "2024-07-06T17:30:00.000Z",
      "pnl_pct": 18.583019999999998,
      "hodl_pct": 25.68653717347621,
      "liquidations": 0,
      "exchange": "okx",
      "hodl_ratio": 0.723453686049544,
      "maxDrawdown": 0,
      "sharpeRatio": -1,
      "_id": "6689ccdadf1e57b18e0e0614"
    },
    "identifier": "optimized_5_1.14_-28_-23-DOGE-USDT-SWAP-qqnF"
  },
  {
    "reward": 329356.1094506208,
    "parameters": {
      "steps": 4,
      "multiplier": 0.95,
      "stopLoss": -18,
      "leverReduce": -16
    },
    "rest": {
      "trades": 59,
      "identifier": "optimized_4_0.95_-18_-16-TURBO-USDT-SWAP-hCHZ",
      "name": "optimized_4_0.95_-18_-16",
      "startCapital": 200,
      "symbol": "TURBO-USDT-SWAP",
      "margin": 39134.68134929138,
      "pnl": 659098.39,
      "winRatio": 0.4745762711864407,
      "time": "2024-07-06T23:06:09.774Z",
      "start": "2024-01-01T00:00:00.000Z",
      "end": "2024-07-06T23:05:00.000Z",
      "pnl_pct": 329549.19412152393,
      "hodl_pct": 793.5726367224206,
      "liquidations": 31,
      "exchange": "okx",
      "hodl_ratio": 415.2728797235421,
      "maxDrawdown": 1901.2792226060878,
      "sharpeRatio": 5.426786439714033,
      "_id": "6689cde1df1e57b18e0e0c30"
    },
    "identifier": "optimized_4_0.95_-18_-16-TURBO-USDT-SWAP-hCHZ"
  },
  {
    "reward": 4786.755103974211,
    "parameters": {
      "steps": 4,
      "multiplier": 0.95,
      "stopLoss": -24,
      "leverReduce": -28
    },
    "rest": {
      "trades": 61,
      "identifier": "optimized_4_0.95_-24_-28-WLD-USDT-SWAP-ISJs",
      "name": "optimized_4_0.95_-24_-28",
      "startCapital": 200,
      "symbol": "WLD-USDT-SWAP",
      "margin": 388.4010278257706,
      "pnl": 9606.91,
      "winRatio": 0.4262295081967213,
      "time": "2024-07-06T23:17:32.088Z",
      "start": "2024-01-01T00:00:00.000Z",
      "end": "2024-07-06T23:16:00.000Z",
      "pnl_pct": 4803.453465584194,
      "hodl_pct": -44.78392513074594,
      "liquidations": 37,
      "exchange": "okx",
      "hodl_ratio": 107.25842925917257,
      "maxDrawdown": 131.2776487824772,
      "sharpeRatio": 4.796755726114703,
      "_id": "6689d08cdf1e57b18e0e1e69"
    },
    "identifier": "optimized_4_0.95_-24_-28-WLD-USDT-SWAP-ISJs"
  },
  {
    "reward": 271.15924697883634,
    "parameters": {
      "steps": 2,
      "multiplier": 0.94,
      "stopLoss": -13,
      "leverReduce": -6
    },
    "rest": {
      "trades": 53,
      "identifier": "optimized_2_0.94_-13_-6-CRV-USDT-SWAP-eOqQ",
      "name": "optimized_2_0.94_-13_-6",
      "startCapital": 200,
      "symbol": "CRV-USDT-SWAP",
      "margin": 33.301177880341875,
      "pnl": 549.84,
      "winRatio": 0.3584905660377358,
      "time": "2024-07-06T23:25:32.685Z",
      "start": "2024-01-01T00:00:00.000Z",
      "end": "2024-07-06T23:24:00.000Z",
      "pnl_pct": 274.92234475558723,
      "hodl_pct": -56.2944582299421,
      "liquidations": 37,
      "exchange": "okx",
      "hodl_ratio": 4.883648469137599,
      "maxDrawdown": 1.683001909750001,
      "sharpeRatio": 38.02211958030139,
      "_id": "6689d26cdf1e57b18e0e28c4"
    },
    "identifier": "optimized_2_0.94_-13_-6-CRV-USDT-SWAP-eOqQ"
  },
  {
    "reward": 117517.90941885702,
    "parameters": {
      "steps": 4,
      "multiplier": 0.94,
      "stopLoss": -17,
      "leverReduce": -25
    },
    "rest": {
      "trades": 129,
      "identifier": "optimized_4_0.94_-17_-25-CEL-USDT-SWAP-kG0U",
      "name": "optimized_4_0.94_-17_-25",
      "startCapital": 200,
      "symbol": "CEL-USDT-SWAP",
      "margin": 60157.3425,
      "pnl": 235320.5,
      "winRatio": 0.3333333333333333,
      "time": "2024-07-06T23:34:40.339Z",
      "start": "2024-01-01T00:00:00.000Z",
      "end": "2024-07-06T23:33:00.000Z",
      "pnl_pct": 117660.25184856856,
      "hodl_pct": 100.66518847006651,
      "liquidations": 87,
      "exchange": "okx",
      "hodl_ratio": 1168.8276119758684,
      "maxDrawdown": 1337.405811429948,
      "sharpeRatio": 6.7748781805103455,
      "_id": "6689d490df1e57b18e0e3555"
    },
    "identifier": "optimized_4_0.94_-17_-25-CEL-USDT-SWAP-kG0U"
  },
  {
    "reward": 67.37686509840177,
    "parameters": {
      "steps": 6,
      "multiplier": 0.95,
      "stopLoss": -18,
      "leverReduce": -15
    },
    "rest": {
      "trades": 29,
      "identifier": "optimized_6_0.95_-18_-15-WIF-USDT-SWAP-fboS",
      "name": "optimized_6_0.95_-18_-15",
      "startCapital": 200,
      "symbol": "WIF-USDT-SWAP",
      "margin": 7.1127451108213835,
      "pnl": 138,
      "winRatio": 0.41379310344827586,
      "time": "2024-07-06T23:48:54.503Z",
      "start": "2024-01-01T00:00:00.000Z",
      "end": "2024-07-06T23:40:00.000Z",
      "pnl_pct": 68.9999296233508,
      "hodl_pct": -32.29834627067162,
      "liquidations": 17,
      "exchange": "okx",
      "hodl_ratio": 2.1363301094460643,
      "maxDrawdown": 0.4727283263271609,
      "sharpeRatio": 25.989643883690658,
      "_id": "6689d7e6df1e57b18e0e4d27"
    },
    "identifier": "optimized_6_0.95_-18_-15-WIF-USDT-SWAP-fboS"
  },
  {
    "reward": 751.2683226875,
    "parameters": {
      "steps": 4,
      "multiplier": 1.01,
      "stopLoss": -29,
      "leverReduce": -10
    },
    "rest": {
      "trades": 3,
      "identifier": "optimized_4_1.01_-29_-10-ZRO-USDT-SWAP-thwi",
      "name": "optimized_4_1.01_-29_-10",
      "startCapital": 200,
      "symbol": "ZRO-USDT-SWAP",
      "margin": 502.47121357370395,
      "pnl": 1502.53,
      "winRatio": 0.6666666666666666,
      "time": "2024-07-06T23:54:01.133Z",
      "start": "2024-01-01T00:00:00.000Z",
      "end": "2024-07-06T23:40:00.000Z",
      "pnl_pct": 751.2637651451951,
      "hodl_pct": 62.65013560635414,
      "liquidations": 1,
      "exchange": "okx",
      "hodl_ratio": 11.991414828940927,
      "maxDrawdown": 0.9667731250000009,
      "sharpeRatio": 1.6454335270205045,
      "_id": "6689d919df1e57b18e0e4fab"
    },
    "identifier": "optimized_4_1.01_-29_-10-ZRO-USDT-SWAP-thwi"
  },
  {
    "reward": 10711.955407847006,
    "parameters": {
      "steps": 2,
      "multiplier": 0.88,
      "stopLoss": -16,
      "leverReduce": -24
    },
    "rest": {
      "trades": 106,
      "identifier": "optimized_2_0.88_-16_-24-ENS-USDT-SWAP-PbrN",
      "name": "optimized_2_0.88_-16_-24",
      "startCapital": 200,
      "symbol": "ENS-USDT-SWAP",
      "margin": 615.8611737148648,
      "pnl": 21445.64,
      "winRatio": 0.330188679245283,
      "time": "2024-07-06T23:55:41.971Z",
      "start": "2024-01-01T00:00:00.000Z",
      "end": "2024-07-06T23:41:00.000Z",
      "pnl_pct": 10722.81942203887,
      "hodl_pct": 170.09606445615123,
      "liquidations": 74,
      "exchange": "okx",
      "hodl_ratio": 63.03978552544987,
      "maxDrawdown": 35.63648756768754,
      "sharpeRatio": -8.226147775524545,
      "_id": "6689d97ddf1e57b18e0e516f"
    },
    "identifier": "optimized_2_0.88_-16_-24-ENS-USDT-SWAP-PbrN"
  },
  {
    "reward": 81.0668144303494,
    "parameters": {
      "steps": 6,
      "multiplier": 0.83,
      "stopLoss": -21,
      "leverReduce": -5
    },
    "rest": {
      "trades": 47,
      "identifier": "optimized_6_0.83_-21_-5-TRB-USDT-SWAP-kofc",
      "name": "optimized_6_0.83_-21_-5",
      "startCapital": 200,
      "symbol": "TRB-USDT-SWAP",
      "margin": 12.422499180000003,
      "pnl": 167.42,
      "winRatio": 0.3191489361702128,
      "time": "2024-07-07T00:18:31.123Z",
      "start": "2024-01-01T00:00:00.000Z",
      "end": "2024-07-06T23:41:00.000Z",
      "pnl_pct": 83.7088781435251,
      "hodl_pct": -57.14285714285714,
      "liquidations": 27,
      "exchange": "okx",
      "hodl_ratio": 1.4649053675116894,
      "maxDrawdown": 0.3893025050166416,
      "sharpeRatio": 44.63844145376487,
      "_id": "6689ded7df1e57b18e0e65cc"
    },
    "identifier": "optimized_6_0.83_-21_-5-TRB-USDT-SWAP-kofc"
  },
  {
    "reward": 47.145769467583335,
    "parameters": {
      "steps": 7,
      "multiplier": 0.94,
      "stopLoss": -26,
      "leverReduce": -12
    },
    "rest": {
      "trades": 9,
      "identifier": "optimized_7_0.94_-26_-12-ULTI-USDT-SWAP-bUJB",
      "name": "optimized_7_0.94_-26_-12",
      "startCapital": 200,
      "symbol": "ULTI-USDT-SWAP",
      "margin": 80.6565,
      "pnl": 95.09,
      "winRatio": 0.4444444444444444,
      "time": "2024-07-07T00:26:55.273Z",
      "start": "2024-01-01T00:00:00.000Z",
      "end": "2024-07-06T23:41:00.000Z",
      "pnl_pct": 47.54734906736308,
      "hodl_pct": -47.340789774024195,
      "liquidations": 5,
      "exchange": "okx",
      "hodl_ratio": 1.0043632413891883,
      "maxDrawdown": 0.32563865749999976,
      "sharpeRatio": 7.711791753759635,
      "_id": "6689e0cfdf1e57b18e0e7190"
    },
    "identifier": "optimized_7_0.94_-26_-12-ULTI-USDT-SWAP-bUJB"
  },
  {
    "reward": 110.4827236625,
    "parameters": {
      "steps": 3,
      "multiplier": 0.87,
      "stopLoss": -29,
      "leverReduce": -24
    },
    "rest": {
      "trades": 16,
      "identifier": "optimized_3_0.87_-29_-24-XRP-USDT-SWAP-H49N",
      "name": "optimized_3_0.87_-29_-24",
      "startCapital": 200,
      "symbol": "XRP-USDT-SWAP",
      "margin": 14.914653684431652,
      "pnl": 222.12,
      "winRatio": 0.5625,
      "time": "2024-07-07T00:31:00.275Z",
      "start": "2024-01-01T00:00:00.000Z",
      "end": "2024-07-06T23:40:00.000Z",
      "pnl_pct": 111.05976949303418,
      "hodl_pct": -27.11313394018205,
      "liquidations": 7,
      "exchange": "okx",
      "hodl_ratio": 4.096161282500878,
      "maxDrawdown": 0.4602633750000008,
      "sharpeRatio": 10.83159251229208,
      "_id": "6689e1c4df1e57b18e0e743c"
    },
    "identifier": "optimized_3_0.87_-29_-24-XRP-USDT-SWAP-H49N"
  },
  {
    "reward": 4992.013887177813,
    "parameters": {
      "steps": 2,
      "multiplier": 0.9,
      "stopLoss": -24,
      "leverReduce": -24
    },
    "rest": {
      "trades": 40,
      "identifier": "optimized_2_0.9_-24_-24-TON-USDT-SWAP-a0W3",
      "name": "optimized_2_0.9_-24_-24",
      "startCapital": 200,
      "symbol": "TON-USDT-SWAP",
      "margin": 442.1506371044776,
      "pnl": 9989.71,
      "winRatio": 0.5,
      "time": "2024-07-07T00:45:44.568Z",
      "start": "2024-01-01T00:00:00.000Z",
      "end": "2024-07-06T23:41:00.000Z",
      "pnl_pct": 4994.855349938285,
      "hodl_pct": 226.93631669535284,
      "liquidations": 22,
      "exchange": "okx",
      "hodl_ratio": 22.009942801017395,
      "maxDrawdown": 7.911128221863219,
      "sharpeRatio": -8.034506962365061,
      "_id": "6689e538df1e57b18e0e7b12"
    },
    "identifier": "optimized_2_0.9_-24_-24-TON-USDT-SWAP-a0W3"
  },
  {
    "reward": 125.47142292459952,
    "parameters": {
      "steps": 2,
      "multiplier": 0.94,
      "stopLoss": -22,
      "leverReduce": -19
    },
    "rest": {
      "trades": 34,
      "identifier": "optimized_2_0.94_-22_-19-FIL-USDT-SWAP-k4Dj",
      "name": "optimized_2_0.94_-22_-19",
      "startCapital": 200,
      "symbol": "FIL-USDT-SWAP",
      "margin": 31.65708408679928,
      "pnl": 255.4,
      "winRatio": 0.5,
      "time": "2024-07-07T00:52:37.543Z",
      "start": "2024-01-01T00:00:00.000Z",
      "end": "2024-07-06T23:41:00.000Z",
      "pnl_pct": 127.7016439756344,
      "hodl_pct": -42.42115971515768,
      "liquidations": 18,
      "exchange": "okx",
      "hodl_ratio": 3.010328921535938,
      "maxDrawdown": 5.785770754004912,
      "sharpeRatio": 12.937856650189637,
      "_id": "6689e6d5df1e57b18e0e80e6"
    },
    "identifier": "optimized_2_0.94_-22_-19-FIL-USDT-SWAP-k4Dj"
  },
  {
    "reward": 722.9424469693846,
    "parameters": {
      "steps": 2,
      "multiplier": 0.88,
      "stopLoss": -14,
      "leverReduce": -28
    },
    "rest": {
      "trades": 26,
      "identifier": "optimized_2_0.88_-14_-28-BNB-USDT-SWAP-giro",
      "name": "optimized_2_0.88_-14_-28",
      "startCapital": 200,
      "symbol": "BNB-USDT-SWAP",
      "margin": 74.08482377260981,
      "pnl": 1449.57,
      "winRatio": 0.38461538461538464,
      "time": "2024-07-07T01:05:27.312Z",
      "start": "2024-01-01T00:00:00.000Z",
      "end": "2024-07-06T23:41:00.000Z",
      "pnl_pct": 724.7852838785533,
      "hodl_pct": 69.40346375881975,
      "liquidations": 17,
      "exchange": "okx",
      "hodl_ratio": 10.443070772335163,
      "maxDrawdown": 2.579376460000002,
      "sharpeRatio": -7.562904851888499,
      "_id": "6689e9d7df1e57b18e0e8831"
    },
    "identifier": "optimized_2_0.88_-14_-28-BNB-USDT-SWAP-giro"
  },
  {
    "reward": 25.41204854001908,
    "parameters": {
      "steps": 5,
      "multiplier": 0.95,
      "stopLoss": -26,
      "leverReduce": -25
    },
    "rest": {
      "trades": 18,
      "identifier": "optimized_5_0.95_-26_-25-SATS-USDT-SWAP-aUs9",
      "name": "optimized_5_0.95_-26_-25",
      "startCapital": 200,
      "symbol": "SATS-USDT-SWAP",
      "margin": 6.3972672014260255,
      "pnl": 52.6,
      "winRatio": 0.3888888888888889,
      "time": "2024-07-07T01:11:54.734Z",
      "start": "2024-01-01T00:00:00.000Z",
      "end": "2024-07-06T23:41:00.000Z",
      "pnl_pct": 26.29870271330485,
      "hodl_pct": -48.746057389029914,
      "liquidations": 9,
      "exchange": "okx",
      "hodl_ratio": 0.5395042003791523,
      "maxDrawdown": 1.0461812664759094,
      "sharpeRatio": 16.18273091063408,
      "_id": "6689eb5adf1e57b18e0e8b1f"
    },
    "identifier": "optimized_5_0.95_-26_-25-SATS-USDT-SWAP-aUs9"
  },
  {
    "reward": 150.02370867152777,
    "parameters": {
      "steps": 6,
      "multiplier": 0.92,
      "stopLoss": -24,
      "leverReduce": -12
    },
    "rest": {
      "trades": 27,
      "identifier": "optimized_6_0.92_-24_-12-MEW-USDT-SWAP-Q6sx",
      "name": "optimized_6_0.92_-24_-12",
      "startCapital": 200,
      "symbol": "MEW-USDT-SWAP",
      "margin": 10.707866765456183,
      "pnl": 302.6,
      "winRatio": 0.5925925925925926,
      "time": "2024-07-07T01:18:32.862Z",
      "start": "2024-01-01T00:00:00.000Z",
      "end": "2024-07-06T23:41:00.000Z",
      "pnl_pct": 151.2988796829083,
      "hodl_pct": -32.21884498480243,
      "liquidations": 14,
      "exchange": "okx",
      "hodl_ratio": 4.695974661856305,
      "maxDrawdown": 0.5406910625000004,
      "sharpeRatio": 20.84124953977842,
      "_id": "6689ece8df1e57b18e0e934d"
    },
    "identifier": "optimized_6_0.92_-24_-12-MEW-USDT-SWAP-Q6sx"
  },
  {
    "reward": 1073.105771911434,
    "parameters": {
      "steps": 7,
      "multiplier": 0.94,
      "stopLoss": -18,
      "leverReduce": -13
    },
    "rest": {
      "trades": 30,
      "identifier": "optimized_7_0.94_-18_-13-UNI-USDT-SWAP-47rS",
      "name": "optimized_7_0.94_-18_-13",
      "startCapital": 200,
      "symbol": "UNI-USDT-SWAP",
      "margin": 35.268836036036035,
      "pnl": 2148.94,
      "winRatio": 0.5666666666666667,
      "time": "2024-07-07T01:33:52.599Z",
      "start": "2024-01-01T00:00:00.000Z",
      "end": "2024-07-06T23:40:00.000Z",
      "pnl_pct": 1074.469405779394,
      "hodl_pct": 13.372093023255804,
      "liquidations": 13,
      "exchange": "okx",
      "hodl_ratio": 80.3516251278504,
      "maxDrawdown": 2.3422808856610366,
      "sharpeRatio": 3.967870302805016,
      "_id": "6689f080df1e57b18e0ea520"
    },
    "identifier": "optimized_7_0.94_-18_-13-UNI-USDT-SWAP-47rS"
  },
  {
    "reward": 4.315837445547224,
    "parameters": {
      "steps": 5,
      "multiplier": 0.93,
      "stopLoss": -28,
      "leverReduce": -21
    },
    "rest": {
      "trades": 15,
      "identifier": "optimized_5_0.93_-28_-21-ETHFI-USDT-SWAP-hsIh",
      "name": "optimized_5_0.93_-28_-21",
      "startCapital": 200,
      "symbol": "ETHFI-USDT-SWAP",
      "margin": 32.90344,
      "pnl": 9.34,
      "winRatio": 0.6666666666666666,
      "time": "2024-07-07T01:38:17.604Z",
      "start": "2024-01-01T00:00:00.000Z",
      "end": "2024-07-06T23:41:00.000Z",
      "pnl_pct": 4.669267020269611,
      "hodl_pct": -41.74918452935694,
      "liquidations": 5,
      "exchange": "okx",
      "hodl_ratio": 0.11184091552701597,
      "maxDrawdown": 0.5416255445277628,
      "sharpeRatio": 14.135873462566867,
      "_id": "6689f189df1e57b18e0ea7cc"
    },
    "identifier": "optimized_5_0.93_-28_-21-ETHFI-USDT-SWAP-hsIh"
  },
  {
    "reward": 5352.869264956229,
    "parameters": {
      "steps": 3,
      "multiplier": 0.91,
      "stopLoss": -27,
      "leverReduce": -7
    },
    "rest": {
      "trades": 25,
      "identifier": "optimized_3_0.91_-27_-7-SHIB-USDT-SWAP-Hdwy",
      "name": "optimized_3_0.91_-27_-7",
      "startCapital": 200,
      "symbol": "SHIB-USDT-SWAP",
      "margin": 252.33112864028925,
      "pnl": 10713.84,
      "winRatio": 0.68,
      "time": "2024-07-07T01:45:51.861Z",
      "start": "2024-01-01T00:00:00.000Z",
      "end": "2024-07-06T23:40:00.000Z",
      "pnl_pct": 5356.921341229578,
      "hodl_pct": 67.02723585087891,
      "liquidations": 9,
      "exchange": "okx",
      "hodl_ratio": 79.92156133586603,
      "maxDrawdown": 33.547350437710854,
      "sharpeRatio": 2.337901654513283,
      "_id": "6689f34fdf1e57b18e0ead16"
    },
    "identifier": "optimized_3_0.91_-27_-7-SHIB-USDT-SWAP-Hdwy"
  },
  {
    "reward": 1852.6101268875711,
    "parameters": {
      "steps": 3,
      "multiplier": 0.92,
      "stopLoss": -16,
      "leverReduce": -22
    },
    "rest": {
      "trades": 44,
      "identifier": "optimized_3_0.92_-16_-22-BCH-USDT-SWAP-YJUv",
      "name": "optimized_3_0.92_-16_-22",
      "startCapital": 200,
      "symbol": "BCH-USDT-SWAP",
      "margin": 123.85756701030932,
      "pnl": 3713.79,
      "winRatio": 0.29545454545454547,
      "time": "2024-07-07T02:07:56.709Z",
      "start": "2024-01-01T00:00:00.000Z",
      "end": "2024-07-06T23:40:00.000Z",
      "pnl_pct": 1856.894506040014,
      "hodl_pct": 31.842713955281432,
      "liquidations": 32,
      "exchange": "okx",
      "hodl_ratio": 58.314580492346174,
      "maxDrawdown": 11.735094760651855,
      "sharpeRatio": 1.3537384640451493,
      "_id": "6689f87cdf1e57b18e0eb631"
    },
    "identifier": "optimized_3_0.92_-16_-22-BCH-USDT-SWAP-YJUv"
  },
  {
    "reward": 1603.2752190210667,
    "parameters": {
      "steps": 2,
      "multiplier": 0.85,
      "stopLoss": -21,
      "leverReduce": -6
    },
    "rest": {
      "trades": 22,
      "identifier": "optimized_2_0.85_-21_-6-BONK-USDT-SWAP-e1YB",
      "name": "optimized_2_0.85_-21_-6",
      "startCapital": 200,
      "symbol": "BONK-USDT-SWAP",
      "margin": 148.6985840425532,
      "pnl": 3210.5,
      "winRatio": 0.5909090909090909,
      "time": "2024-07-07T02:21:06.062Z",
      "start": "2024-01-01T00:00:00.000Z",
      "end": "2024-07-06T23:41:00.000Z",
      "pnl_pct": 1605.2515726092058,
      "hodl_pct": 61.53309618469693,
      "liquidations": 11,
      "exchange": "okx",
      "hodl_ratio": 26.087612555540904,
      "maxDrawdown": 10.520537062061685,
      "sharpeRatio": 0.6003865671961072,
      "_id": "6689fb92df1e57b18e0ec128"
    },
    "identifier": "optimized_2_0.85_-21_-6-BONK-USDT-SWAP-e1YB"
  },
  {
    "reward": 85.26826570208212,
    "parameters": {
      "steps": 2,
      "multiplier": 0.83,
      "stopLoss": -21,
      "leverReduce": -23
    },
    "rest": {
      "trades": 90,
      "identifier": "optimized_2_0.83_-21_-23-LDO-USDT-SWAP-PMng",
      "name": "optimized_2_0.83_-21_-23",
      "startCapital": 200,
      "symbol": "LDO-USDT-SWAP",
      "margin": 20.781381630546957,
      "pnl": 181.94,
      "winRatio": 0.36666666666666664,
      "time": "2024-07-07T02:29:46.292Z",
      "start": "2024-01-01T00:00:00.000Z",
      "end": "2024-07-06T23:41:00.000Z",
      "pnl_pct": 90.9710122992892,
      "hodl_pct": -38.45283018867924,
      "liquidations": 57,
      "exchange": "okx",
      "hodl_ratio": 2.365781968529111,
      "maxDrawdown": 1.1173429791787803,
      "sharpeRatio": 75.48768469565351,
      "_id": "6689fd9adf1e57b18e0ecb21"
    },
    "identifier": "optimized_2_0.83_-21_-23-LDO-USDT-SWAP-PMng"
  },
  {
    "reward": 305.27217305749997,
    "parameters": {
      "steps": 3,
      "multiplier": 0.84,
      "stopLoss": -20,
      "leverReduce": -21
    },
    "rest": {
      "trades": 32,
      "identifier": "optimized_3_0.84_-20_-21-LTC-USDT-SWAP-NMQ4",
      "name": "optimized_3_0.84_-20_-21",
      "startCapital": 200,
      "symbol": "LTC-USDT-SWAP",
      "margin": 28.748915056799905,
      "pnl": 614.64,
      "winRatio": 0.40625,
      "time": "2024-07-07T02:34:38.070Z",
      "start": "2024-01-01T00:00:00.000Z",
      "end": "2024-07-06T23:41:00.000Z",
      "pnl_pct": 307.3180117973837,
      "hodl_pct": -10.282811641954982,
      "liquidations": 20,
      "exchange": "okx",
      "hodl_ratio": 29.88657407119012,
      "maxDrawdown": 1.6970194249999992,
      "sharpeRatio": 8.156704699786244,
      "_id": "6689febedf1e57b18e0ece1f"
    },
    "identifier": "optimized_3_0.84_-20_-21-LTC-USDT-SWAP-NMQ4"
  },
  {
    "reward": 147860.99497516284,
    "parameters": {
      "steps": 2,
      "multiplier": 0.87,
      "stopLoss": -26,
      "leverReduce": -28
    },
    "rest": {
      "trades": 88,
      "identifier": "optimized_2_0.87_-26_-28-FLOKI-USDT-SWAP-YUKu",
      "name": "optimized_2_0.87_-26_-28",
      "startCapital": 200,
      "symbol": "FLOKI-USDT-SWAP",
      "margin": 12566.678223615721,
      "pnl": 296065.19,
      "winRatio": 0.4772727272727273,
      "time": "2024-07-07T02:49:44.556Z",
      "start": "2024-01-01T00:00:00.000Z",
      "end": "2024-07-06T23:40:00.000Z",
      "pnl_pct": 148032.59669587083,
      "hodl_pct": 334.8211731044349,
      "liquidations": 48,
      "exchange": "okx",
      "hodl_ratio": 442.12435947023465,
      "maxDrawdown": 1669.4320665534597,
      "sharpeRatio": 5.352759638108595,
      "_id": "668a0248df1e57b18e0edd51"
    },
    "identifier": "optimized_2_0.87_-26_-28-FLOKI-USDT-SWAP-YUKu"
  },
  {
    "reward": 787.2434072946013,
    "parameters": {
      "steps": 3,
      "multiplier": 0.85,
      "stopLoss": -16,
      "leverReduce": -23
    },
    "rest": {
      "trades": 66,
      "identifier": "optimized_3_0.85_-16_-23-AVAX-USDT-SWAP-wYma",
      "name": "optimized_3_0.85_-16_-23",
      "startCapital": 200,
      "symbol": "AVAX-USDT-SWAP",
      "margin": 39.8452148755027,
      "pnl": 1584.48,
      "winRatio": 0.3181818181818182,
      "time": "2024-07-07T02:56:38.317Z",
      "start": "2024-01-01T00:00:00.000Z",
      "end": "2024-07-06T23:40:00.000Z",
      "pnl_pct": 792.2383008136202,
      "hodl_pct": -29.050988931228446,
      "liquidations": 44,
      "exchange": "okx",
      "hodl_ratio": 27.270613839999136,
      "maxDrawdown": 6.920472508533542,
      "sharpeRatio": 15.302817502223315,
      "_id": "668a03e6df1e57b18e0ee34e"
    },
    "identifier": "optimized_3_0.85_-16_-23-AVAX-USDT-SWAP-wYma"
  },
  {
    "reward": 18.817622083794703,
    "parameters": {
      "steps": 5,
      "multiplier": 0.93,
      "stopLoss": -29,
      "leverReduce": -21
    },
    "rest": {
      "trades": 32,
      "identifier": "optimized_5_0.93_-29_-21-INJ-USDT-SWAP-tnPR",
      "name": "optimized_5_0.93_-29_-21",
      "startCapital": 200,
      "symbol": "INJ-USDT-SWAP",
      "margin": 6.363083394957983,
      "pnl": 39.16,
      "winRatio": 0.625,
      "time": "2024-07-07T03:05:15.320Z",
      "start": "2024-01-01T00:00:00.000Z",
      "end": "2024-07-06T23:40:00.000Z",
      "pnl_pct": 19.57775361734634,
      "hodl_pct": -43.55172606725228,
      "liquidations": 9,
      "exchange": "okx",
      "hodl_ratio": 0.4495287646490636,
      "maxDrawdown": 0.49877916205295675,
      "sharpeRatio": 31.147590589851372,
      "_id": "668a05ebdf1e57b18e0eec7b"
    },
    "identifier": "optimized_5_0.93_-29_-21-INJ-USDT-SWAP-tnPR"
  },
  {
    "reward": 875.0909063026833,
    "parameters": {
      "steps": 2,
      "multiplier": 0.81,
      "stopLoss": -13,
      "leverReduce": -24
    },
    "rest": {
      "trades": 114,
      "identifier": "optimized_2_0.81_-13_-24-SUI-USDT-SWAP-c0vL",
      "name": "optimized_2_0.81_-13_-24",
      "startCapital": 200,
      "symbol": "SUI-USDT-SWAP",
      "margin": 72.26992440794781,
      "pnl": 1769.57,
      "winRatio": 0.32456140350877194,
      "time": "2024-07-07T03:11:40.442Z",
      "start": "2024-01-01T00:00:00.000Z",
      "end": "2024-07-06T23:40:00.000Z",
      "pnl_pct": 884.7832058701164,
      "hodl_pct": -10.425257731958759,
      "liquidations": 82,
      "exchange": "okx",
      "hodl_ratio": 84.86919255317807,
      "maxDrawdown": 15.91462118369228,
      "sharpeRatio": 11.968260976946066,
      "_id": "668a076cdf1e57b18e0ef537"
    },
    "identifier": "optimized_2_0.81_-13_-24-SUI-USDT-SWAP-c0vL"
  },
  {
    "reward": 6203.44256795434,
    "parameters": {
      "steps": 3,
      "multiplier": 0.88,
      "stopLoss": -23,
      "leverReduce": -8
    },
    "rest": {
      "trades": 37,
      "identifier": "optimized_3_0.88_-23_-8-NEAR-USDT-SWAP-Iwp5",
      "name": "optimized_3_0.88_-23_-8",
      "startCapital": 200,
      "symbol": "NEAR-USDT-SWAP",
      "margin": 386.59982127659566,
      "pnl": 12416.08,
      "winRatio": 0.5945945945945946,
      "time": "2024-07-07T03:22:09.915Z",
      "start": "2024-01-01T00:00:00.000Z",
      "end": "2024-07-06T23:41:00.000Z",
      "pnl_pct": 6208.042226419523,
      "hodl_pct": 31.9539599890381,
      "liquidations": 17,
      "exchange": "okx",
      "hodl_ratio": 194.28084120244284,
      "maxDrawdown": 30.758104240387382,
      "sharpeRatio": 4.787182748075416,
      "_id": "668a09e1df1e57b18e0efff5"
    },
    "identifier": "optimized_3_0.88_-23_-8-NEAR-USDT-SWAP-Iwp5"
  },
  {
    "reward": -22.58665082134435,
    "parameters": {
      "steps": 8,
      "multiplier": 0.88,
      "stopLoss": -28,
      "leverReduce": -13
    },
    "rest": {
      "trades": 31,
      "identifier": "optimized_8_0.88_-28_-13-OP-USDT-SWAP-0fHy",
      "name": "optimized_8_0.88_-28_-13",
      "startCapital": 200,
      "symbol": "OP-USDT-SWAP",
      "margin": 2.7037223234759358,
      "pnl": -42.83,
      "winRatio": 0.5483870967741935,
      "time": "2024-07-07T03:38:40.318Z",
      "start": "2024-01-01T00:00:00.000Z",
      "end": "2024-07-06T23:41:00.000Z",
      "pnl_pct": -21.417450476177017,
      "hodl_pct": -60.15610281254206,
      "liquidations": 13,
      "exchange": "okx",
      "hodl_ratio": -0.356031216698294,
      "maxDrawdown": 0.3616695037660809,
      "sharpeRatio": 30.89921087738265,
      "_id": "668a0dc0df1e57b18e0f0efe"
    },
    "identifier": "optimized_8_0.88_-28_-13-OP-USDT-SWAP-0fHy"
  },
  {
    "reward": -13.878669098348658,
    "parameters": {
      "steps": 10,
      "multiplier": 0.92,
      "stopLoss": -18,
      "leverReduce": -17
    },
    "rest": {
      "trades": 34,
      "identifier": "optimized_10_0.92_-18_-17-W-USDT-SWAP-5vVv",
      "name": "optimized_10_0.92_-18_-17",
      "startCapital": 200,
      "symbol": "W-USDT-SWAP",
      "margin": 1.6294090523968783,
      "pnl": -24.4,
      "winRatio": 0.47058823529411764,
      "time": "2024-07-07T03:42:37.432Z",
      "start": "2024-01-01T00:00:00.000Z",
      "end": "2024-07-06T23:40:00.000Z",
      "pnl_pct": -12.200491222488255,
      "hodl_pct": -50.0513698630137,
      "liquidations": 18,
      "exchange": "okx",
      "hodl_ratio": -0.24375938672367914,
      "maxDrawdown": 0.198455689368916,
      "sharpeRatio": 33.981856781543605,
      "_id": "668a0eaddf1e57b18e0f1310"
    },
    "identifier": "optimized_10_0.92_-18_-17-W-USDT-SWAP-5vVv"
  },
  {
    "reward": 148.6029549125,
    "parameters": {
      "steps": 4,
      "multiplier": 0.84,
      "stopLoss": -24,
      "leverReduce": -25
    },
    "rest": {
      "trades": 36,
      "identifier": "optimized_4_0.84_-24_-25-ADA-USDT-SWAP-RIjP",
      "name": "optimized_4_0.84_-24_-25",
      "startCapital": 200,
      "symbol": "ADA-USDT-SWAP",
      "margin": 11.985791218229515,
      "pnl": 301.15,
      "winRatio": 0.4166666666666667,
      "time": "2024-07-07T03:47:44.885Z",
      "start": "2024-01-01T00:00:00.000Z",
      "end": "2024-07-06T23:41:00.000Z",
      "pnl_pct": 150.57384964454346,
      "hodl_pct": -37.67261704277535,
      "liquidations": 20,
      "exchange": "okx",
      "hodl_ratio": 3.996904421945905,
      "maxDrawdown": 0.9704508749999988,
      "sharpeRatio": 26.180764144251278,
      "_id": "668a0fe0df1e57b18e0f1868"
    },
    "identifier": "optimized_4_0.84_-24_-25-ADA-USDT-SWAP-RIjP"
  },
  {
    "reward": 3795.9412234906245,
    "parameters": {
      "steps": 2,
      "multiplier": 0.9,
      "stopLoss": -29,
      "leverReduce": -7
    },
    "rest": {
      "trades": 38,
      "identifier": "optimized_2_0.9_-29_-7-LPT-USDT-SWAP-pcFK",
      "name": "optimized_2_0.9_-29_-7",
      "startCapital": 200,
      "symbol": "LPT-USDT-SWAP",
      "margin": 647.2519175891143,
      "pnl": 7602.83,
      "winRatio": 0.6842105263157895,
      "time": "2024-07-07T04:06:59.747Z",
      "start": "2024-01-01T00:00:00.000Z",
      "end": "2024-07-06T23:40:00.000Z",
      "pnl_pct": 3801.4171879962587,
      "hodl_pct": 71.38364779874213,
      "liquidations": 17,
      "exchange": "okx",
      "hodl_ratio": 53.25333329439693,
      "maxDrawdown": 39.79039667270583,
      "sharpeRatio": 1.1843770368722248,
      "_id": "668a1463df1e57b18e0f29fa"
    },
    "identifier": "optimized_2_0.9_-29_-7-LPT-USDT-SWAP-pcFK"
  },
  {
    "reward": 248.7124278839286,
    "parameters": {
      "steps": 6,
      "multiplier": 0.86,
      "stopLoss": -22,
      "leverReduce": -22
    },
    "rest": {
      "trades": 35,
      "identifier": "optimized_6_0.86_-22_-22-LINK-USDT-SWAP-bMjr",
      "name": "optimized_6_0.86_-22_-22",
      "startCapital": 200,
      "symbol": "LINK-USDT-SWAP",
      "margin": 10.939287805758319,
      "pnl": 501.73,
      "winRatio": 0.37142857142857144,
      "time": "2024-07-07T04:13:03.096Z",
      "start": "2024-01-01T00:00:00.000Z",
      "end": "2024-07-06T23:41:00.000Z",
      "pnl_pct": 250.86350582219566,
      "hodl_pct": -12.077617932418867,
      "liquidations": 22,
      "exchange": "okx",
      "hodl_ratio": 20.770942351870996,
      "maxDrawdown": 0.6400068750000005,
      "sharpeRatio": 12.919705111449536,
      "_id": "668a15cfdf1e57b18e0f2e97"
    },
    "identifier": "optimized_6_0.86_-22_-22-LINK-USDT-SWAP-bMjr"
  },
  {
    "reward": 683.2055116557365,
    "parameters": {
      "steps": 2,
      "multiplier": 0.9,
      "stopLoss": -18,
      "leverReduce": -21
    },
    "rest": {
      "trades": 100,
      "identifier": "optimized_2_0.9_-18_-21-STX-USDT-SWAP-jtew",
      "name": "optimized_2_0.9_-18_-21",
      "startCapital": 200,
      "symbol": "STX-USDT-SWAP",
      "margin": 71.54415346153846,
      "pnl": 1381.77,
      "winRatio": 0.36,
      "time": "2024-07-07T04:27:38.902Z",
      "start": "2024-01-01T00:00:00.000Z",
      "end": "2024-07-06T23:40:00.000Z",
      "pnl_pct": 690.8835102090908,
      "hodl_pct": -1.4225606090963798,
      "liquidations": 66,
      "exchange": "okx",
      "hodl_ratio": 485.6619154159939,
      "maxDrawdown": 11.874883442634498,
      "sharpeRatio": 6.689212042816795,
      "_id": "668a193adf1e57b18e0f3b8a"
    },
    "identifier": "optimized_2_0.9_-18_-21-STX-USDT-SWAP-jtew"
  },
  {
    "reward": 4.265100511722973,
    "parameters": {
      "steps": 9,
      "multiplier": 0.94,
      "stopLoss": -12,
      "leverReduce": -10
    },
    "rest": {
      "trades": 37,
      "identifier": "optimized_9_0.94_-12_-10-MATIC-USDT-SWAP-5bqL",
      "name": "optimized_9_0.94_-12_-10",
      "startCapital": 200,
      "symbol": "MATIC-USDT-SWAP",
      "margin": 2.9296608722205884,
      "pnl": 13.84,
      "winRatio": 0.24324324324324326,
      "time": "2024-07-07T04:38:21.014Z",
      "start": "2024-01-01T00:00:00.000Z",
      "end": "2024-07-06T23:41:00.000Z",
      "pnl_pct": 6.920798007342306,
      "hodl_pct": -47.873107426099494,
      "liquidations": 27,
      "exchange": "okx",
      "hodl_ratio": 0.1445654644003581,
      "maxDrawdown": 0.27872461249999897,
      "sharpeRatio": 36.732370288191895,
      "_id": "668a1bbddf1e57b18e0f40e4"
    },
    "identifier": "optimized_9_0.94_-12_-10-MATIC-USDT-SWAP-5bqL"
  }
]