[
  {
    "reward": 14884.933076923076,
    "parameters": {
      "steps": 3,
      "multiplier": 0.93,
      "stopLoss": -14,
      "leverReduce": -15
    },
    "rest": {
      "trades": 78,
      "identifier": "optimization_3_0.93_-14_-15-RSR-USDT-SWAP-yjRO",
      "name": "optimization_3_0.93_-14_-15",
      "startCapital": 200,
      "symbol": "RSR-USDT-SWAP",
      "margin": 1137.8958670368593,
      "pnl": 29789.62,
      "winRatio": 0.41025641025641024,
      "time": "2024-07-03T22:18:20.557Z",
      "start": "2024-02-01T00:00:00.000Z",
      "end": "2024-07-02T20:32:00.000Z",
      "pnl_pct": 14894.808935300403,
      "hodl_pct": 152.5080533824206,
      "liquidations": 50,
      "exchange": "okx",
      "hodl_ratio": 97.66572062887079,
      "maxDrawdown": -143.31347885653983,
      "_id": "6685ce2cb9852f00f520be6a"
    },
    "identifier": "optimization_3_0.93_-14_-15-RSR-USDT-SWAP-yjRO"
  }
]